cbar_currency_rates/__init__.py
cbar_currency_rates/rates.py
cbar_currency_rates-1.1.0.dist-info/LICENSE
cbar_currency_rates-1.1.0.dist-info/METADATA
cbar_currency_rates-1.1.0.dist-info/WHEEL
cbar_currency_rates-1.1.0.dist-info/top_level.txt
cbar_currency_rates-1.1.0.dist-info/RECORD
