Metadata-Version: 2.1
Name: cbar-currency-rates
Version: 1.1.0
Summary: A Python library for fetching currency rates from the Central Bank of Azerbaijan Republic (CBAR) XML file.
Home-page: https://github.com/zmmmdf/cbar-currency-rates
Author: Ziya Mammadov
Author-email: ziyamm08@gmail.com
License: MIT
Classifier: License :: OSI Approved :: MIT License
Classifier: Programming Language :: Python :: 3
Classifier: Programming Language :: Python :: 3.6
Classifier: Programming Language :: Python :: 3.7
Classifier: Programming Language :: Python :: 3.8
Classifier: Programming Language :: Python :: 3.9
Classifier: Programming Language :: Python :: 3.10
Requires-Python: >=3.6
License-File: LICENSE
Requires-Dist: requests
Requires-Dist: xmltodict
